{"cameraMode":{"drawMode":0,"name":"Shaded","section":"Shading Mode"},"sceneLighting":true,"audioPlay":false,"sceneViewState":{"m_AlwaysRefresh":false,"showFog":true,"showSkybox":true,"showFlares":true,"showImageEffects":true,"showParticleSystems":true,"showVisualEffectGraphs":true,"m_FxEnabled":true},"in2DMode":false,"pivot":{"x":-0.6644858717918396,"y":18.171527862548829,"z":-17.559127807617189},"rotation":{"x":0.2907121479511261,"y":0.0573732852935791,"z":-0.017465554177761079,"w":0.9549886584281921},"size":3.1500260829925539,"orthographic":false}